{
  "18-0": {
    "castingTime": "南明鲁王朱以海监国时期（公元1645年—1646年）。",
    "material": "黄铜（铜锌合金），铜含量约55%—65%，锌含量约25%—35%。南明鲁王监国时期铸币。黄铜钱呈金黄色，表面多呈深褐色包浆。",
    "dimensions": "小平直径约2.5厘米，重约3—3.5克。",
    "obverseFeatures": "* 圆形方孔\n* 面文\"大明通宝\"四字楷书直读，为国号钱\n* 光背为主",
    "castingCraft": "采用范铸法（铜范或砂范），一范多钱。大明通宝为南明鲁王朱以海在浙江绍兴监国时铸行（公元1645年—1646年）。制作流程为：先雕刻大明通宝阴文母范（含面文\"大明通宝\"四字，楷书），中央方孔设金属芯；合范浇铸熔融黄铜液，冷却脱范后逐枚修整。鲁王政权存在时间短，铸期极短，铸量极少。",
    "coreBackground": "* 南明鲁王朱以海在浙江绍兴监国时铸，铸期极短\n* 鲁王政权存在时间短，铸量极少\n* 据《中国钱币大辞典》记载，大明通宝为南明钱币中的稀少品种",
    "variants": "* **小平光背版**：背面无文\n* **小平背星版**：背面铸星纹",
    "valueReference": "",
    "valueTable": [
      {
        "variant": "小平光背",
        "grade": "普品",
        "priceRange": "500—1000元",
        "notes": ""
      },
      {
        "variant": "小平光背",
        "grade": "美品",
        "priceRange": "1000—3000元",
        "notes": ""
      },
      {
        "variant": "小平光背",
        "grade": "极美品",
        "priceRange": "3000—5000元",
        "notes": ""
      }
    ],
    "images": {
      "main": "",
      "variants": []
    }
  },
  "18-1": {
    "castingTime": "南明福王朱由崧弘光元年（公元1645年）。",
    "material": "黄铜（铜锌合金），铜含量约55%—65%，锌含量约25%—35%。南明弘光政权铸币，延续明后期黄铜铸币传统。黄铜钱呈金黄色，表面多呈深褐色包浆。",
    "dimensions": "* 小平直径：约2.5厘米，重约3—3.5克\n* 折二直径：约2.8厘米",
    "obverseFeatures": "* 圆形方孔\n* 面文\"弘光通宝\"楷书直读\n* 分小平和折二两种\n* 小平有南京版、凤阳版、桂林版、贵阳版、背星版多种版别\n* 折二钱较少见",
    "castingCraft": "采用范铸法（铜范或砂范），一范多钱。弘光通宝为南明福王朱由崧弘光元年（公元1645年）在南京即位后铸行。制作流程为：先雕刻弘光通宝阴文母范（含面文\"弘光通宝\"四字，楷书），中央方孔设金属芯；合范浇铸熔融黄铜液，冷却脱范后逐枚修整。铸期仅一年即清军南下攻破南京，版别较多，反映了南明初期多局铸钱的状况。",
    "coreBackground": "* 南明福王朱由崧在南京即位后铸，铸期仅一年即清军南下攻破南京\n* 弘光通宝版别较多，反映了南明初期多局铸钱的状况\n* 据《中国钱币大辞典》记载，弘光通宝为南明铸币中较常见的品种",
    "variants": "* **小平南京版**：铸于南京\n* **小平凤阳版**：铸于凤阳\n* **小平桂林版**：铸于桂林\n* **小平贵阳版**：铸于贵阳\n* **小平背星版**：背面铸星纹\n* **折二版**：较少见",
    "valueReference": "",
    "valueTable": [
      {
        "variant": "小平（常见版）",
        "grade": "普品",
        "priceRange": "100—200元",
        "notes": ""
      },
      {
        "variant": "小平（常见版）",
        "grade": "美品",
        "priceRange": "200—500元",
        "notes": ""
      },
      {
        "variant": "小平（常见版）",
        "grade": "极美品",
        "priceRange": "500—1000元",
        "notes": ""
      },
      {
        "variant": "小平（少见版）",
        "grade": "美品",
        "priceRange": "300—800元",
        "notes": ""
      },
      {
        "variant": "折二",
        "grade": "美品",
        "priceRange": "500—1500元",
        "notes": ""
      }
    ],
    "images": {
      "main": "",
      "variants": []
    }
  },
  "18-2": {
    "castingTime": "南明唐王朱聿键隆武年间（公元1645年—1646年）。",
    "material": "黄铜（铜锌合金），铜含量约55%—65%，锌含量约25%—35%。南明隆武政权铸币。黄铜钱呈金黄色，表面多呈深褐色包浆。",
    "dimensions": "* 小平直径：约2.5厘米，重约3—3.5克\n* 折二直径：约2.9厘米，重约8.88克",
    "obverseFeatures": "* 圆形方孔\n* 面文\"隆武通宝\"楷书直读\n* 有小平、折二两种\n* 铸于福建",
    "castingCraft": "采用范铸法（铜范或砂范），一范多钱。隆武通宝为南明唐王朱聿键在福州即位后铸于福建（公元1645年—1646年）。制作流程为：先雕刻隆武通宝阴文母范（含面文\"隆武通宝\"四字，楷书），中央方孔设金属芯；合范浇铸熔融黄铜液，冷却脱范后逐枚修整。唐王政权存在时间短，铸期仅一年余，铸量有限。",
    "coreBackground": "* 南明唐王朱聿键在福州即位后铸于福建，铸期仅一年余\n* 唐王政权存在时间短，铸量有限\n* 据《中国钱币大辞典》记载，隆武通宝存世较少",
    "variants": "* **小平版**：楷书直读，光背\n* **小平大字版**：钱文字体较大\n* **折二版**：较少见",
    "valueReference": "",
    "valueTable": [
      {
        "variant": "小平",
        "grade": "普品",
        "priceRange": "300—500元",
        "notes": ""
      },
      {
        "variant": "小平",
        "grade": "美品",
        "priceRange": "500—1500元",
        "notes": ""
      },
      {
        "variant": "小平",
        "grade": "极美品",
        "priceRange": "1500—3000元",
        "notes": ""
      },
      {
        "variant": "折二",
        "grade": "美品",
        "priceRange": "1000—3000元",
        "notes": ""
      }
    ],
    "images": {
      "main": "",
      "variants": []
    }
  },
  "18-3": {
    "castingTime": "南明桂王朱由榔永历年间（公元1646年—1661年）。",
    "material": "黄铜（铜锌合金），铜含量约55%—65%，锌含量约25%—35%。南明永历政权铸币，铸行时间较长，铜质参差。黄铜钱呈金黄色至暗黄色，表面多呈深褐色包浆。",
    "dimensions": "* 小平直径：约2.5厘米，重约3—4克\n* 折十型背上壹下分者直径4.55厘米，孔径0.9厘米，厚度0.2厘米，重22.5克",
    "obverseFeatures": "* 圆形方孔\n* 面文\"永历通宝\"楷书直读\n* 有小平、折二、折五、折十四种面值\n* 钱背铸有星月纹及多种文字\n* 铸造大小厚薄不一，版别复杂",
    "castingCraft": "采用范铸法（铜范或砂范），一范多钱。永历通宝为南明桂王朱由榔永历年间（公元1646年—1661年）在广东肇庆即位后铸行。制作流程为：先雕刻永历通宝阴文母范（含面文\"永历通宝\"四字，楷书），中央方孔设金属芯；合范浇铸熔融黄铜液，冷却脱范后逐枚修整。是南明政权中持续时间最长的铸币，铸造大小厚薄不一，铜质参差，版别极为复杂。",
    "coreBackground": "* 南明桂王朱由榔在广东肇庆即位后铸\n* 是南明政权中持续时间最长的铸币，也是南明钱币中版别最为复杂的品种\n* 永历帝流亡缅甸后被俘，南明覆亡\n* 据《中国钱币大辞典》记载，永历通宝版别极为丰富",
    "variants": "* **小平光背版**：背面无文\n* **小平背星月版**：背面铸星纹或月纹\n* **折二版**：背铸纪值文字\n* **折五版**：背铸纪值文字\n* **折十版**：背上\"壹\"下\"分\"，直径约4.55厘米\n* **兴朝通宝式版**：与兴朝通宝风格相近的版别",
    "valueReference": "",
    "valueTable": [
      {
        "variant": "小平光背",
        "grade": "普品",
        "priceRange": "100—200元",
        "notes": ""
      },
      {
        "variant": "小平光背",
        "grade": "美品",
        "priceRange": "200—500元",
        "notes": ""
      },
      {
        "variant": "小平光背",
        "grade": "极美品",
        "priceRange": "500—1000元",
        "notes": ""
      },
      {
        "variant": "小平背星月",
        "grade": "美品",
        "priceRange": "300—800元",
        "notes": ""
      },
      {
        "variant": "折二",
        "grade": "美品",
        "priceRange": "500—1500元",
        "notes": ""
      },
      {
        "variant": "折五",
        "grade": "美品",
        "priceRange": "800—2000元",
        "notes": ""
      },
      {
        "variant": "折十",
        "grade": "美品",
        "priceRange": "1000—3000元",
        "notes": ""
      },
      {
        "variant": "折十",
        "grade": "极美品",
        "priceRange": "3000—5000元",
        "notes": ""
      }
    ],
    "images": {
      "main": "",
      "variants": []
    }
  }
}